pyfpga/__init__.py
pyfpga/diamond.py
pyfpga/factory.py
pyfpga/ise.py
pyfpga/libero.py
pyfpga/openflow.py
pyfpga/project.py
pyfpga/quartus.py
pyfpga/vivado.py
pyfpga/helpers/bitprog.py
pyfpga/helpers/hdl2bit.py
pyfpga/helpers/prj2bit.py
pyfpga/templates/diamond-prog.jinja
pyfpga/templates/diamond.jinja
pyfpga/templates/ise-prog.jinja
pyfpga/templates/ise.jinja
pyfpga/templates/libero-prog.jinja
pyfpga/templates/libero.jinja
pyfpga/templates/openflow-prog.jinja
pyfpga/templates/openflow.jinja
pyfpga/templates/quartus-prog.jinja
pyfpga/templates/quartus.jinja
pyfpga/templates/vivado-prog.jinja
pyfpga/templates/vivado.jinja
pyfpga-0.4.0.dist-info/licenses/LICENSE
pyfpga-0.4.0.dist-info/METADATA
pyfpga-0.4.0.dist-info/WHEEL
pyfpga-0.4.0.dist-info/entry_points.txt
pyfpga-0.4.0.dist-info/top_level.txt
pyfpga-0.4.0.dist-info/RECORD
